src/traffic_light/__init__.py
src/traffic_light/traffic_light.py
src/traffic_light/version.py
ctomkow_traffic_light-0.0.1.dist-info/METADATA
ctomkow_traffic_light-0.0.1.dist-info/WHEEL
ctomkow_traffic_light-0.0.1.dist-info/RECORD
