Metadata-Version: 2.1
Name: ctomkow_traffic-light
Version: 0.0.1
Summary: traffic light backend
Author-email: Craig Abt Tomkow <ctomkow@gmail.com>
Classifier: Development Status :: 3 - Alpha
Classifier: License :: OSI Approved :: MIT License
Classifier: Natural Language :: English
Classifier: Operating System :: OS Independent
Classifier: Programming Language :: Python
Classifier: Programming Language :: Python :: 3.8
Classifier: Programming Language :: Python :: 3.9
Classifier: Programming Language :: Python :: 3.10
Classifier: Programming Language :: Python :: 3.11
Classifier: Programming Language :: Python :: 3.12
Requires-Python: >=3.8
Requires-Dist: fastapi~=0.104.1
Requires-Dist: gpiod~=2.1.3
